openeo_aggregator/__init__.py
openeo_aggregator/about.py
openeo_aggregator/app.py
openeo_aggregator/backend.py
openeo_aggregator/caching.py
openeo_aggregator/connection.py
openeo_aggregator/constants.py
openeo_aggregator/egi.py
openeo_aggregator/errors.py
openeo_aggregator/federation_extension.py
openeo_aggregator/testing.py
openeo_aggregator/utils.py
openeo_aggregator/background/__init__.py
openeo_aggregator/background/prime_caches.py
openeo_aggregator/config/__init__.py
openeo_aggregator/config/config.py
openeo_aggregator/config/examples/aggregator.dummy.py
openeo_aggregator/config/examples/gunicorn-config.py
openeo_aggregator/metadata/__init__.py
openeo_aggregator/metadata/merging.py
openeo_aggregator/metadata/reporter.py
openeo_aggregator/metadata/utils.py
openeo_aggregator/metadata/validator.py
openeo_aggregator/metadata/models/__init__.py
openeo_aggregator/metadata/models/cube_dimension.py
openeo_aggregator/metadata/models/cube_dimensions.py
openeo_aggregator/metadata/models/extent.py
openeo_aggregator/metadata/models/spatial_extent.py
openeo_aggregator/metadata/models/stac_eo.py
openeo_aggregator/metadata/models/stac_summaries.py
openeo_aggregator/metadata/models/statistics.py
openeo_aggregator/metadata/models/temporal_extent.py
openeo_aggregator/partitionedjobs/__init__.py
openeo_aggregator/partitionedjobs/crossbackend.py
openeo_aggregator/partitionedjobs/splitting.py
openeo_aggregator/partitionedjobs/tracking.py
openeo_aggregator/partitionedjobs/zookeeper.py
openeo_aggregator-0.47.0a1.data/data/openeo-aggregator-data/CHANGELOG.md
openeo_aggregator-0.47.0a1.dist-info/licenses/LICENSE.txt
openeo_aggregator-0.47.0a1.dist-info/METADATA
openeo_aggregator-0.47.0a1.dist-info/WHEEL
openeo_aggregator-0.47.0a1.dist-info/entry_points.txt
openeo_aggregator-0.47.0a1.dist-info/top_level.txt
openeo_aggregator-0.47.0a1.dist-info/RECORD
