Metadata-Version: 2.4
Name: openeo-aggregator
Version: 0.47.0a1
Summary: openEO Aggregator Backend Implementation.
Home-page: https://github.com/Open-EO/openeo-aggregator
Author: Stefaan Lippens
Author-email: stefaan.lippens@vito.be
Classifier: Programming Language :: Python :: 3
Classifier: License :: OSI Approved :: Apache Software License
Classifier: Development Status :: 3 - Alpha
Classifier: Operating System :: OS Independent
Requires-Python: >=3.11
License-File: LICENSE.txt
Requires-Dist: requests
Requires-Dist: attrs
Requires-Dist: openeo>=0.42.0
Requires-Dist: openeo_driver>=0.136.0.a2.dev
Requires-Dist: flask~=2.0
Requires-Dist: gunicorn~=20.0
Requires-Dist: python-json-logger>=2.0.0
Requires-Dist: kazoo~=2.8.0
Provides-Extra: dev
Requires-Dist: pytest>=6.2.0; extra == "dev"
Requires-Dist: requests-mock>=1.9.0; extra == "dev"
Requires-Dist: dirty-equals>=0.7.0; extra == "dev"
Dynamic: author
Dynamic: author-email
Dynamic: classifier
Dynamic: home-page
Dynamic: license-file
Dynamic: provides-extra
Dynamic: requires-dist
Dynamic: requires-python
Dynamic: summary
